README.md
setup.py
gabutcat/__init__.py
gabutcat/behavior.py
gabutcat.egg-info/PKG-INFO
gabutcat.egg-info/SOURCES.txt
gabutcat.egg-info/dependency_links.txt
gabutcat.egg-info/top_level.txt