Metadata-Version: 2.4
Name: gabutcat
Version: 0.1
Summary: Library lucu untuk mensimulasikan kebiasaan kucing saat gabut
Author: Nama Kamu
Author-email: emailkamu@example.com
Classifier: Programming Language :: Python :: 3
Classifier: License :: OSI Approved :: MIT License
Classifier: Operating System :: OS Independent
Requires-Python: >=3.6
Dynamic: author
Dynamic: author-email
Dynamic: classifier
Dynamic: requires-python
Dynamic: summary
